understory/apps/indieauth_client/__init__.py
understory/apps/indieauth_client/templates/__init__.py
understory/apps/indieauth_client/templates/guests.html
understory/apps/indieauth_client/templates/signin.html
understory/apps/indieauth_client/templates/signout.html
understory_indieauth_client-0.0.6.dist-info/entry_points.txt
understory_indieauth_client-0.0.6.dist-info/LICENSE
understory_indieauth_client-0.0.6.dist-info/WHEEL
understory_indieauth_client-0.0.6.dist-info/METADATA
understory_indieauth_client-0.0.6.dist-info/RECORD
